convbot_fastapi/__init__.py
convbot_fastapi/__main__.py
convbot_fastapi/convbot_fastapi.py
convbot_fastapi/force_async.py
LICENSE
convbot_fastapi-0.1.0.dist-info/LICENSE
convbot_fastapi-0.1.0.dist-info/WHEEL
convbot_fastapi-0.1.0.dist-info/METADATA
convbot_fastapi-0.1.0.dist-info/RECORD
