Metadata-Version: 2.1
Name: convbot-fastapi
Version: 0.1.0
Summary: Convbot with fastapi
Home-page: https://github.com/ffreemt/convbot-fastapi
License: MIT
Author: ffreemt
Requires-Python: >=3.7,<4.0
Classifier: License :: OSI Approved :: MIT License
Classifier: Programming Language :: Python :: 3
Classifier: Programming Language :: Python :: 3.7
Classifier: Programming Language :: Python :: 3.8
Classifier: Programming Language :: Python :: 3.9
Requires-Dist: fastapi (>=0.63.0,<0.64.0)
Requires-Dist: logzero (>=1.7.0,<2.0.0)
Requires-Dist: pydantic[dotenv] (>=1.8.1,<2.0.0)
Requires-Dist: torch (>=1.9.0,<2.0.0); python_version >= "3.7" and python_version < "4.0" and sys_platform == "linux"
Requires-Dist: transformers (>=4.9.0,<5.0.0)
Requires-Dist: uvicorn (>=0.14.0,<0.15.0)
Project-URL: Repository, https://github.com/ffreemt/convbot-fastapi
